streamlit_scrollable_textbox/__init__.py
streamlit_scrollable_textbox/frontend/build/asset-manifest.json
streamlit_scrollable_textbox/frontend/build/bootstrap.min.css
streamlit_scrollable_textbox/frontend/build/index.html
streamlit_scrollable_textbox/frontend/build/precache-manifest.674bf56b3943c5bfd74a5d79ed40a07b.js
streamlit_scrollable_textbox/frontend/build/precache-manifest.ce59e6adbdfa2804482993b9d113cfc9.js
streamlit_scrollable_textbox/frontend/build/service-worker.js
streamlit_scrollable_textbox/frontend/build/static/js/2.65af5637.chunk.js
streamlit_scrollable_textbox/frontend/build/static/js/2.65af5637.chunk.js.LICENSE.txt
streamlit_scrollable_textbox/frontend/build/static/js/2.65af5637.chunk.js.map
streamlit_scrollable_textbox/frontend/build/static/js/2.728b8a60.chunk.js
streamlit_scrollable_textbox/frontend/build/static/js/2.728b8a60.chunk.js.LICENSE.txt
streamlit_scrollable_textbox/frontend/build/static/js/2.728b8a60.chunk.js.map
streamlit_scrollable_textbox/frontend/build/static/js/main.39598afe.chunk.js
streamlit_scrollable_textbox/frontend/build/static/js/main.39598afe.chunk.js.map
streamlit_scrollable_textbox/frontend/build/static/js/main.97ecb5c4.chunk.js
streamlit_scrollable_textbox/frontend/build/static/js/main.97ecb5c4.chunk.js.map
streamlit_scrollable_textbox/frontend/build/static/js/runtime-main.c4ba6c12.js
streamlit_scrollable_textbox/frontend/build/static/js/runtime-main.c4ba6c12.js.map
streamlit_scrollable_textbox-0.0.3.dist-info/LICENSE
streamlit_scrollable_textbox-0.0.3.dist-info/METADATA
streamlit_scrollable_textbox-0.0.3.dist-info/WHEEL
streamlit_scrollable_textbox-0.0.3.dist-info/top_level.txt
streamlit_scrollable_textbox-0.0.3.dist-info/RECORD
