Metadata-Version: 2.1
Name: streamlit_scrollable_textbox
Version: 0.0.3
Summary: Scrollable textbox for Streamlit.
Home-page: https://github.com/RobertoFN/streamlit-scrollable-textbox
Author: Roberto Frias Nerio
Author-email: robertofnerio@gmail.com
Requires-Python: >=3.6
License-File: LICENSE
